tl/__init__.py
tl/exp.py
tl/experiments/exp1.py
tl/experiments/exp10.py
tl/experiments/exp2.py
tl/experiments/exp3.py
tl/experiments/exp4.py
tl/experiments/exp5.py
tl/experiments/exp6.py
tl/experiments/exp7.py
tl/experiments/exp8.py
tl/experiments/exp9.py
tl_exp_kec-0.1.2.dist-info/METADATA
tl_exp_kec-0.1.2.dist-info/WHEEL
tl_exp_kec-0.1.2.dist-info/top_level.txt
tl_exp_kec-0.1.2.dist-info/RECORD
